roibaview/__init__.py
roibaview/controller.py
roibaview/data_handler.py
roibaview/data_plotter.py
roibaview/gui.py
roibaview/gui_utils.py
roibaview/main.py
roibaview/ventral_root.py
roibaview/video_viewer.py
roibaview/plugins/base.py
roibaview/plugins/basic_filters.py
roibaview/plugins/basic_transformations.py
roibaview/plugins/basic_utils.py
roibaview/plugins/caiman_motion_correction.py
roibaview/plugins/cut_out_region.py
roibaview/plugins/loader.py
roibaview/plugins/peak_detection.py
roibaview/plugins/ventral_root_detection.py
roibaview/plugins/video_converter.py
roibaview-0.1.9.dist-info/licenses/LICENSE
roibaview-0.1.9.dist-info/METADATA
roibaview-0.1.9.dist-info/WHEEL
roibaview-0.1.9.dist-info/entry_points.txt
roibaview-0.1.9.dist-info/top_level.txt
roibaview-0.1.9.dist-info/RECORD
