Metadata-Version: 2.4
Name: roibaview
Version: 0.1.9
Summary: A PyQt6-based application for ROI visualization.
Home-page: https://github.com/UniNilsBrehm/roibaview
Author: Nils
Author-email: Nils <your.email@example.com>
License: MIT
Requires-Python: >=3.7
License-File: LICENSE
Requires-Dist: PyQt6
Requires-Dist: pyqtgraph
Requires-Dist: numpy
Requires-Dist: pandas
Requires-Dist: scipy
Requires-Dist: h5py
Requires-Dist: tifftools
Requires-Dist: tifffile
Requires-Dist: opencv-python
Requires-Dist: ffmpy
Requires-Dist: joblib
Requires-Dist: platformdirs
Requires-Dist: roifile
Dynamic: author
Dynamic: home-page
Dynamic: license-file
Dynamic: requires-python
